{
  "code": 200,
  "list": [
    {
      "key": "一 JAVA基础面试",
      "data": [
        {
          "title": "1 java基础面试知识点",
          "path": "/java/base/base.json"
        },{
          "title": "2 java深入源码级的面试题",
          "path": "/java/source/base.json"
        },{
          "title": "3 数据结构",
          "path": "/java/base/base.json"
        },{
          "title": "4 线程、多线程和线程池",
          "path": "/java/base/base.json"
        },{
          "title": "5 并发编程有关知识点",
          "path": "/java/base/base.json"
        }
      ]
    },
    {
      "key": "二 Android基础面试",
      "data": [
        {
          "title": "1 Android基础知识点",
          "path": "/android/base/base.json"
        },
        {
          "title": "2 Android源码相关分析",
          "path": "/android/base/base.json"
        },
        {
          "title": "3 常见的一些原理性问题",
          "path": "/android/base/base.json"
        },
        {
          "title": "4 开发中常见的一些问题",
          "path": "/android/base/base.json"
        }
      ]
    },
    {
      "key": "三 Android高端Android技术",
      "data": [
        {
          "title": "1 图片处理技术",
          "path": "/android/base/base.json"
        },
        {
          "title": "2 网络和安全机制",
          "path": "/android/base/base.json"
        },
        {
          "title": "3 数据库",
          "path": "/android/base/base.json"
        },
        {
          "title": "4 算法",
          "path": "/android/base/base.json"
        },
        {
          "title": "5 插件化、模块化、组件化、热修复、增量更新、Gradle",
          "path": "/android/base/base.json"
        },
        {
          "title": "6 架构设计和设计模式",
          "path": "/android/base/base.json"
        },
        {
          "title": "7 性能优化",
          "path": "/android/base/base.json"
        },
        {
          "title": "8 NDK、jni、Binder、AIDL、进程通信有关",
          "path": "/android/base/base.json"
        },
        {
          "title": "9 framework层、ROM定制、Ubuntu、Linux之类的问题",
          "path": "/android/base/base.json"
        }
      ]
    },
    {
      "key": "三 技术总结",
      "data": [
        {
          "title": "1 公司面试",
          "path": "/result/result.json"
        },{
          "title": "2 技术总结",
          "path": "/result/result2.json"
        }
      ]
    }
  ]
}